kabinet/__init__.py
kabinet/arkitekt.py
kabinet/errors.py
kabinet/funcs.py
kabinet/kabinet.py
kabinet/rath.py
kabinet/rekuest.py
kabinet/scalars.py
kabinet/api/project.json
kabinet/api/schema.graphql
kabinet/api/schema.py
kabinet-0.10.0.dist-info/METADATA
kabinet-0.10.0.dist-info/WHEEL
kabinet-0.10.0.dist-info/RECORD
