Metadata-Version: 2.4
Name: kabinet
Version: 0.10.0
Author-email: jhnnsrs <jhnnsrs@gmail.com>
Requires-Python: >=3.11
Requires-Dist: rath>=3.6
Requires-Dist: websockets>=15.0.1
